{"items":[{"id":"202532400000100399","nm":"㈜소모에너지 성내주유소","lat":37.5332,"lng":127.1218,"addr":"서울특별시 강동구 올림픽로 578","isOpenAtNight":"N","hasBell":"N","male":1,"female":1,"type":"공중화장실"},{"id":"202532400000100318","nm":"샛마을근린공원","lat":37.5497,"lng":127.1475,"addr":"서울특별시 강동구 구천면로 441(공원)","isOpenAtNight":"N","hasBell":"Y","male":3,"female":4,"type":"공중화장실"},{"id":"202532400000100363","nm":"동우빌딩","lat":37.5349,"lng":127.1385,"addr":"서울특별시 강동구 양재대로 1443","isOpenAtNight":"N","hasBell":"Y","male":2,"female":2,"type":"개방화장실"},{"id":"202532400000100295","nm":"성내하니공원","lat":37.5294,"lng":127.1266,"addr":"서울특별시 강동구 성내로3가길 71","isOpenAtNight":"N","hasBell":"Y","male":2,"female":4,"type":"공중화장실"},{"id":"202532400000100441","nm":"강동구청 본관 화장실","lat":37.5301,"lng":127.1239,"addr":"서울특별시 강동구 성내로 25","isOpenAtNight":"N","hasBell":"Y","male":2,"female":3,"type":"개방화장실"},{"id":"202532400000100371","nm":"신라빌딩","lat":37.5393,"lng":127.1233,"addr":"서울특별시 강동구 천호대로 997","isOpenAtNight":"N","hasBell":"Y","male":2,"female":2,"type":"개방화장실"},{"id":"202532400000100312","nm":"철봉공원(고덕약수터)","lat":37.5608,"lng":127.1601,"addr":"서울특별시 강동구 동남로 990","isOpenAtNight":"N","hasBell":"Y","male":0,"female":1,"type":"공중화장실"},{"id":"202532400000100316","nm":"명일파출소 뒤","lat":37.5536,"lng":127.1561,"addr":"서울특별시 강동구 동남로 895","isOpenAtNight":"N","hasBell":"Y","male":1,"female":1,"type":"공중화장실"},{"id":"202532400000100438","nm":"보훈의학연구소 1층 화장실","lat":37.5286751,"lng":127.1472819,"addr":"서울특별시 강동구 진황도로 61길 53","isOpenAtNight":"N","hasBell":"N","male":0,"female":0,"type":"개방화장실"},{"id":"202532400000100442","nm":"강동구청 제2청사 화장실","lat":37.5299,"lng":127.1244,"addr":"서울특별시 강동구 성내로 25","isOpenAtNight":"N","hasBell":"Y","male":2,"female":3,"type":"개방화장실"},{"id":"202532400000100302","nm":"명일근린공원(중앙하이츠 뒷산)","lat":37.5523,"lng":127.1595,"addr":"서울특별시 강동구 상일동 산54","isOpenAtNight":"N","hasBell":"Y","male":1,"female":2,"type":"공중화장실"},{"id":"202532400000100311","nm":"동명근린공원(축구장)","lat":37.5611,"lng":127.1644,"addr":"서울특별시 강동구 아리수로78길 23(공원)","isOpenAtNight":"N","hasBell":"Y","male":1,"female":3,"type":"공중화장실"},{"id":"202532400000100404","nm":"방아다리 주유소","lat":37.546,"lng":127.1555,"addr":"서울특별시 강동구 동남로 811","isOpenAtNight":"N","hasBell":"N","male":1,"female":1,"type":"공중화장실"},{"id":"202532400000100450","nm":"암사도서관 화장실","lat":37.552799,"lng":127.133364,"addr":"서울특별시 강동구 고덕로 20길 42","isOpenAtNight":"N","hasBell":"Y","male":1,"female":2,"type":"개방화장실"},{"id":"202532400000100416","nm":"고덕1동주민센터 화장실","lat":37.5572592,"lng":127.1515131,"addr":"서울특별시 강동구 양재대로156길 123","isOpenAtNight":"N","hasBell":"Y","male":4,"female":8,"type":"개방화장실"},{"id":"202532400000100328","nm":"능골근린공원","lat":37.5565,"lng":127.1745,"addr":"서울특별시 강동구 상일동 536(공원)","isOpenAtNight":"N","hasBell":"Y","male":1,"female":3,"type":"공중화장실"},{"id":"202532400000100422","nm":"천호1동주민센터 화장실","lat":37.545,"lng":127.1368,"addr":"서울특별시 강동구 구천면로42길 59","isOpenAtNight":"N","hasBell":"Y","male":4,"female":8,"type":"개방화장실"},{"id":"202532400000100297","nm":"일자산숲속화장실","lat":37.529,"lng":127.1492,"addr":"서울특별시 강동구 동남로 614","isOpenAtNight":"N","hasBell":"Y","male":2,"female":4,"type":"공중화장실"},{"id":"202532400000100411","nm":"강일동주민센터 화장실","lat":37.5652,"lng":127.1739,"addr":"서울특별시 강동구 아리수로93길9-14","isOpenAtNight":"N","hasBell":"Y","male":2,"female":4,"type":"개방화장실"},{"id":"202532400000100358","nm":"강동구립 해공노인복지관(신관) 화장실","lat":37.546159,"lng":127.131724,"addr":"서울특별시 강동구 천중로 17길 42-16","isOpenAtNight":"N","hasBell":"Y","male":3,"female":7,"type":"개방화장실"},{"id":"202532400000100393","nm":"시립강동청소년센터","lat":37.5668,"lng":127.1731,"addr":"서울특별시 강동구 아리수로 93길 47","isOpenAtNight":"N","hasBell":"Y","male":2,"female":3,"type":"개방화장실"},{"id":"202532400000100322","nm":"당말어린이공원","lat":37.5389,"lng":127.1329,"addr":"서울특별시 강동구 진황도로29길 34","isOpenAtNight":"N","hasBell":"Y","male":1,"female":2,"type":"공중화장실"},{"id":"202532400000100303","nm":"명일근린공원(상일동산)","lat":37.5497,"lng":127.1651,"addr":"서울특별시 강동구 상일동 185","isOpenAtNight":"N","hasBell":"Y","male":0,"female":1,"type":"공중화장실"},{"id":"202532400000100356","nm":"선사체험교실 화장실","lat":37.5625,"lng":127.1325,"addr":"서울특별시 강동구 올림픽로 875","isOpenAtNight":"N","hasBell":"Y","male":2,"female":6,"type":"개방화장실"},{"id":"202532400000100390","nm":"강동소방서 화장실","lat":37.5297,"lng":127.125,"addr":"서울특별시 강동구 성내로39","isOpenAtNight":"N","hasBell":"Y","male":2,"female":0,"type":"개방화장실"},{"id":"202532400000100448","nm":"둔촌도서관 화장실","lat":37.531562,"lng":127.148332,"addr":"서울특별시 강동구 동남로 49길 21-8","isOpenAtNight":"N","hasBell":"Y","male":1,"female":1,"type":"개방화장실"},{"id":"202532400000100428","nm":"성내3동 주민센터 화장실","lat":37.5261,"lng":127.1328,"addr":"서울특별시 강동구 강동대로53길 76","isOpenAtNight":"N","hasBell":"Y","male":1,"female":3,"type":"개방화장실"},{"id":"202532400000100387","nm":"강동구의회 화장실","lat":37.5286,"lng":127.1264,"addr":"서울특별시 강동구 성내로 55","isOpenAtNight":"N","hasBell":"N","male":13,"female":11,"type":"개방화장실"},{"id":"202532400000100374","nm":"시온캐슬빌딩","lat":37.5539,"lng":127.1439,"addr":"서울특별시 강동구 양재대로 1661","isOpenAtNight":"N","hasBell":"Y","male":2,"female":2,"type":"개방화장실"},{"id":"202532400000100452","nm":"해공도서관 화장실","lat":37.543874,"lng":127.125513,"addr":"서울특별시 강동구 올림픽로 702","isOpenAtNight":"N","hasBell":"Y","male":2,"female":2,"type":"개방화장실"},{"id":"202532400000100334","nm":"명일테니스장 화장실","lat":37.5445404,"lng":127.1537817,"addr":"서울특별시 강동구 동남로 785","isOpenAtNight":"N","hasBell":"Y","male":1,"female":1,"type":"개방화장실"},{"id":"202532400000100359","nm":"서경빌딩","lat":37.5302,"lng":127.1229,"addr":"서울특별시 강동구 성내로 19","isOpenAtNight":"N","hasBell":"Y","male":3,"female":3,"type":"개방화장실"},{"id":"202532400000100296","nm":"선린어린이공원","lat":37.5285,"lng":127.1372,"addr":"서울특별시 강동구 양재대로91길 59","isOpenAtNight":"N","hasBell":"Y","male":2,"female":4,"type":"공중화장실"},{"id":"202532400000100472","nm":"5호선 천호역","lat":37.538462,"lng":127.122905,"addr":"서울특별시 강동구 천호동 455 천호역(5 또는 8호선)","isOpenAtNight":"N","hasBell":"Y","male":5,"female":16,"type":"개방화장실"},{"id":"202532400000100381","nm":"둔촌역전통시장 공영주차장내고객지원센터","lat":37.5285,"lng":127.1339,"addr":"서울특별시 강동구 풍성로54길 21","isOpenAtNight":"N","hasBell":"Y","male":1,"female":2,"type":"개방화장실"},{"id":"202532400000100378","nm":"나비상가","lat":37.5384,"lng":127.1273,"addr":"서울특별시 강동구 천호대로157길 14","isOpenAtNight":"N","hasBell":"Y","male":3,"female":2,"type":"개방화장실"},{"id":"202532400000100400","nm":"천호 현대주유소","lat":37.5451,"lng":127.1295,"addr":"서울특별시 강동구 천중로 67","isOpenAtNight":"N","hasBell":"N","male":1,"female":1,"type":"공중화장실"},{"id":"202532400000100421","nm":"암사3동주민센터 화장실","lat":37.555,"lng":127.1409,"addr":"서울특별시 강동구 고덕로 137","isOpenAtNight":"N","hasBell":"Y","male":10,"female":14,"type":"개방화장실"},{"id":"202532400000100369","nm":"태성프라자","lat":37.5515,"lng":127.1277,"addr":"서울특별시 강동구 올림픽로 787","isOpenAtNight":"N","hasBell":"Y","male":4,"female":4,"type":"개방화장실"},{"id":"202532400000100439","nm":"치과병원 2층 로비 화장실","lat":37.5297883,"lng":127.1484678,"addr":"서울특별시 강동구 진황도로 61길 53","isOpenAtNight":"N","hasBell":"Y","male":2,"female":4,"type":"개방화장실"},{"id":"202532400000100469","nm":"8호선 암사역사공원역역","lat":37.557155,"lng":127.13732,"addr":"서울특별시 강동구 아리수로27길 2","isOpenAtNight":"N","hasBell":"Y","male":3,"female":8,"type":"개방화장실"},{"id":"202532400000100430","nm":"둔촌1동 주민센터 화장실","lat":37.5231,"lng":127.1415,"addr":"서울특별시 강동구 양재대로84길 31","isOpenAtNight":"N","hasBell":"Y","male":1,"female":2,"type":"개방화장실"},{"id":"202532400000100418","nm":"암사1동주민센터 화장실","lat":37.5514726,"lng":127.132669,"addr":"서울특별시 강동구 올림로98가길 57","isOpenAtNight":"N","hasBell":"Y","male":2,"female":1,"type":"개방화장실"},{"id":"202532400000100394","nm":"삼표에너지 고덕주유소","lat":37.5551,"lng":127.1297,"addr":"서울특별시 강동구 고덕로 39","isOpenAtNight":"N","hasBell":"N","male":1,"female":1,"type":"공중화장실"},{"id":"202532400000100330","nm":"여울빛공원","lat":37.574,"lng":127.1687,"addr":"서울특별시 강동구 강일동 170-1","isOpenAtNight":"N","hasBell":"Y","male":3,"female":8,"type":"공중화장실"},{"id":"202532400000100380","nm":"길동빌딩","lat":37.5359,"lng":127.1396,"addr":"서울특별시 강동구 양재대로 1458","isOpenAtNight":"N","hasBell":"Y","male":2,"female":2,"type":"개방화장실"},{"id":"202532400000100338","nm":"강동구민회관 화장실","lat":37.5457033,"lng":127.141156,"addr":"서울특별시 강동구 상암로 168","isOpenAtNight":"N","hasBell":"Y","male":2,"female":3,"type":"개방화장실"},{"id":"202532400000100307","nm":"민속의집","lat":37.5596,"lng":127.1684,"addr":"서울특별시 강동구 고덕로83길55","isOpenAtNight":"N","hasBell":"Y","male":0,"female":1,"type":"공중화장실"},{"id":"202532400000100397","nm":"광성주유소","lat":37.5416,"lng":127.1242,"addr":"서울특별시 강동구 올림픽로 673","isOpenAtNight":"N","hasBell":"N","male":1,"female":2,"type":"공중화장실"},{"id":"202532400000100467","nm":"5호선 상일동역","lat":37.557055,"lng":127.166995,"addr":"서울특별시 강동구 상일동 148 상일동역","isOpenAtNight":"N","hasBell":"Y","male":3,"female":8,"type":"개방화장실"},{"id":"202532400000100443","nm":"강동구청 서관 화장실","lat":37.5304,"lng":127.1236,"addr":"서울특별시 강동구 성내로 25","isOpenAtNight":"N","hasBell":"Y","male":3,"female":4,"type":"개방화장실"},{"id":"202532400000100454","nm":"신세계 이마트 명일점 공중화장실","lat":37.5547,"lng":127.1559,"addr":"서울특별시 강동구 고덕로 276","isOpenAtNight":"N","hasBell":"Y","male":7,"female":13,"type":"개방화장실"},{"id":"202532400000100408","nm":"비자인터내셔날㈜암사충전소 화장실","lat":37.5518,"lng":127.1279,"addr":"서울특별시 강동구 암사동 503-30","isOpenAtNight":"N","hasBell":"N","male":2,"female":1,"type":"공중화장실"},{"id":"202532400000100326","nm":"고덕그라시움(135동 앞)","lat":37.5602,"lng":127.1623,"addr":"서울특별시 강동구 고덕동 692(공원)","isOpenAtNight":"N","hasBell":"Y","male":2,"female":4,"type":"공중화장실"},{"id":"202532400000100470","nm":"8호선 암사역","lat":37.550646,"lng":127.125659,"addr":"서울특별시 강동구 암사동 501 암사역","isOpenAtNight":"N","hasBell":"Y","male":4,"female":10,"type":"개방화장실"},{"id":"202532400000100314","nm":"방죽근린공원","lat":37.5567,"lng":127.1586,"addr":"서울특별시 강동구 고덕2동 296","isOpenAtNight":"N","hasBell":"Y","male":0,"female":1,"type":"공중화장실"},{"id":"202532400000100340","nm":"강동그린웨이가족캠핑장 화장실","lat":37.5361071,"lng":127.1533068,"addr":"서울특별시 강동구 천호대로206길 87","isOpenAtNight":"N","hasBell":"Y","male":2,"female":5,"type":"개방화장실"},{"id":"202532400000100429","nm":"길동주민센터 화장실","lat":37.5344625,"lng":127.142715,"addr":"서울특별시 강동구 천호대로 1183","isOpenAtNight":"N","hasBell":"Y","male":2,"female":4,"type":"개방화장실"},{"id":"202532400000100417","nm":"고덕2동주민센터 화장실","lat":37.5605,"lng":127.1644,"addr":"서울특별시 강동구 아리수로78길 43-12","isOpenAtNight":"N","hasBell":"Y","male":1,"female":1,"type":"개방화장실"},{"id":"202532400000100365","nm":"일성오피스텔","lat":37.5352,"lng":127.1363,"addr":"서울특별시 강동구 천호대로 1121","isOpenAtNight":"N","hasBell":"Y","male":3,"female":3,"type":"개방화장실"},{"id":"202532400000100360","nm":"브라운스톤 천호","lat":37.538,"lng":127.1237,"addr":"서울특별시 강동구 천호대로 1006","isOpenAtNight":"N","hasBell":"Y","male":3,"female":4,"type":"개방화장실"},{"id":"202532400000100315","nm":"두레근린공원","lat":37.5586,"lng":127.1517,"addr":"서울특별시 강동구 고덕동 497(공원)","isOpenAtNight":"N","hasBell":"Y","male":0,"female":1,"type":"공중화장실"},{"id":"202532400000100344","nm":"안말공영주차장 화장실","lat":37.53168,"lng":127.13,"addr":"서울특별시 강동구 풍성로45길 11","isOpenAtNight":"N","hasBell":"Y","male":0,"female":1,"type":"개방화장실"},{"id":"202532400000100332","nm":"온조대왕문화체육관 화장실","lat":37.5581855,"lng":127.1586598,"addr":"서울특별시  강동구 고덕로 285","isOpenAtNight":"N","hasBell":"Y","male":2,"female":3,"type":"개방화장실"},{"id":"202532400000100410","nm":"천호보건지소 화장실","lat":37.547,"lng":127.1337,"addr":"서울특별시 강동구 구천면로297-5","isOpenAtNight":"N","hasBell":"Y","male":2,"female":6,"type":"개방화장실"},{"id":"202532400000100341","nm":"해공문화체육관 화장실","lat":37.5421191,"lng":127.1298669,"addr":"서울특별시 강동구 천중로 18길 61","isOpenAtNight":"N","hasBell":"Y","male":1,"female":3,"type":"개방화장실"},{"id":"202532400000100468","nm":"8호선 강동구청역","lat":37.538374,"lng":127.115484,"addr":"서울특별시 강동구 성내동 319 강동구청역","isOpenAtNight":"N","hasBell":"Y","male":3,"female":7,"type":"개방화장실"},{"id":"202532400000100370","nm":"삼정빌딩","lat":37.5499,"lng":127.1272,"addr":"서울특별시 강동구 올림픽로 769","isOpenAtNight":"N","hasBell":"Y","male":2,"female":2,"type":"개방화장실"},{"id":"202532400000100412","nm":"상일1동 주민센터 화장실","lat":37.55071,"lng":127.168361,"addr":"서울특별시 강동구 구천면로 633","isOpenAtNight":"N","hasBell":"Y","male":7,"female":15,"type":"개방화장실"},{"id":"202532400000100434","nm":"2관 1층 화장실","lat":37.5297854,"lng":127.1481285,"addr":"서울특별시 강동구 진황도로 61길 53","isOpenAtNight":"N","hasBell":"Y","male":2,"female":3,"type":"개방화장실"},{"id":"202532400000100339","nm":"민속의집 화장실","lat":37.5598189,"lng":127.1675496,"addr":"서울특별시 강동구 고덕로83길 55","isOpenAtNight":"N","hasBell":"Y","male":1,"female":0,"type":"개방화장실"},{"id":"202532400000100329","nm":"가제골(전원마을)","lat":37.564,"lng":127.1484,"addr":"서울특별시 강동구 고덕동 산94-1","isOpenAtNight":"N","hasBell":"Y","male":1,"female":3,"type":"공중화장실"},{"id":"202532400000100471","nm":"5호선 강동역","lat":37.53594,"lng":127.1299,"addr":"서울특별시 강동구 천호동 447 강동역","isOpenAtNight":"N","hasBell":"Y","male":5,"female":13,"type":"개방화장실"},{"id":"202532400000100375","nm":"강동그린타워","lat":37.5346,"lng":127.1382,"addr":"서울특별시 강동구 천호대로 1139","isOpenAtNight":"N","hasBell":"Y","male":3,"female":4,"type":"개방화장실"},{"id":"202532400000100357","nm":"강동노인종합복지관 화장실","lat":37.5525,"lng":127.1543,"addr":"서울특별시 강동구 동남로71길 32-5","isOpenAtNight":"N","hasBell":"Y","male":10,"female":12,"type":"개방화장실"},{"id":"202532400000100414","nm":"명일1동 주민센터 화장실","lat":37.55162,"lng":127.1442,"addr":"서울특별시 강동구 양재대로1634","isOpenAtNight":"N","hasBell":"N","male":2,"female":3,"type":"개방화장실"},{"id":"202532400000100449","nm":"성내도서관 화장실","lat":37.532824,"lng":127.133319,"addr":"서울특별시 강동구 성안로 106-1","isOpenAtNight":"N","hasBell":"Y","male":5,"female":10,"type":"개방화장실"},{"id":"202532400000100376","nm":"소망빌딩","lat":37.53,"lng":127.1315,"addr":"서울특별시 강동구 성안로 71","isOpenAtNight":"N","hasBell":"Y","male":1,"female":1,"type":"개방화장실"},{"id":"202532400000100427","nm":"성내2동주민센터 화장실","lat":37.5324,"lng":127.1295,"addr":"서울특별시 강동구 풍성로37가길 62","isOpenAtNight":"N","hasBell":"N","male":3,"female":3,"type":"개방화장실"},{"id":"202532400000100336","nm":"고덕어울림수영장 화장실","lat":37.5577148,"lng":127.1700554,"addr":"서울특별시 강동구 고덕로399","isOpenAtNight":"N","hasBell":"Y","male":3,"female":8,"type":"개방화장실"},{"id":"202532400000100391","nm":"강동도서관본관동개방화장실","lat":37.538492,"lng":127.14377,"addr":"서울특별시 강동구 양재대로116길57","isOpenAtNight":"N","hasBell":"Y","male":11,"female":15,"type":"개방화장실"},{"id":"202532400000100458","nm":"홈플러스 강동점","lat":37.5457,"lng":127.1423,"addr":"서울특별시 강동구 양재대로 1571","isOpenAtNight":"N","hasBell":"N","male":3,"female":4,"type":"개방화장실"},{"id":"202532400000100355","nm":"박물관 앞 화장실","lat":37.5609,"lng":127.1316,"addr":"서울특별시 강동구 올림픽로 875","isOpenAtNight":"N","hasBell":"Y","male":2,"female":3,"type":"개방화장실"},{"id":"202532400000100435","nm":"종합재활센터 1층 화장실","lat":37.5290561,"lng":127.148338,"addr":"서울특별시 강동구 진황도로 61길 53","isOpenAtNight":"N","hasBell":"Y","male":3,"female":4,"type":"개방화장실"},{"id":"202532400000100432","nm":"중앙관 2층 로비 화장실","lat":37.5306445,"lng":127.148223,"addr":"서울특별시 강동구 진황도로 61길 53","isOpenAtNight":"N","hasBell":"Y","male":2,"female":8,"type":"개방화장실"},{"id":"202532400000100466","nm":"5호선 굽은다리역","lat":37.545539,"lng":127.140717,"addr":"서울특별시 강동구 명일동 345-12 굽은다리역","isOpenAtNight":"N","hasBell":"Y","male":3,"female":7,"type":"개방화장실"},{"id":"202532400000100382","nm":"암사종합시장 고객화장실","lat":37.550216,"lng":127.128869,"addr":"서울특별시 강동구 상암로11길 8, 2층","isOpenAtNight":"N","hasBell":"Y","male":2,"female":3,"type":"개방화장실"},{"id":"202532400000100396","nm":"지에스칼텍스㈜동서울주유소","lat":37.5452,"lng":127.1703,"addr":"서울특별시 강동구 천호대로 1456","isOpenAtNight":"N","hasBell":"N","male":1,"female":1,"type":"공중화장실"},{"id":"202532400000100403","nm":"㈜퍼스트오일 코알라주유소","lat":37.531,"lng":127.1211,"addr":"서울특별시 강동구 올림픽로 556","isOpenAtNight":"N","hasBell":"N","male":1,"female":2,"type":"공중화장실"},{"id":"202532400000100366","nm":"힐탑오피스텔","lat":37.5366,"lng":127.1314,"addr":"서울특별시 강동구 천호대로 1073","isOpenAtNight":"N","hasBell":"Y","male":3,"female":6,"type":"개방화장실"},{"id":"202532400000100299","nm":"일자산 제1체육관 뒤쪽","lat":37.5328,"lng":127.1529,"addr":"서울특별시 강동구 둔촌동 산125","isOpenAtNight":"N","hasBell":"Y","male":1,"female":1,"type":"공중화장실"},{"id":"202532400000100464","nm":"5호선 둔촌동역","lat":37.527657,"lng":127.134042,"addr":"서울특별시 강동구 둔촌동 416 둔촌동역","isOpenAtNight":"N","hasBell":"Y","male":3,"female":8,"type":"개방화장실"},{"id":"202532400000100367","nm":"길동복조리시장고객화장실","lat":37.5371,"lng":127.1432,"addr":"서울특별시 강동구 천호대로187길 62","isOpenAtNight":"N","hasBell":"N","male":2,"female":6,"type":"개방화장실"},{"id":"202532400000100433","nm":"3관 1층 화장실","lat":37.5293031,"lng":127.1476447,"addr":"서울특별시 강동구 진황도로 61길 53","isOpenAtNight":"N","hasBell":"Y","male":3,"female":5,"type":"개방화장실"},{"id":"202532400000100301","nm":"일자산자연공원(허브천문공원)","lat":37.5377,"lng":127.1538,"addr":"서울특별시 강동구 둔촌2동 산86","isOpenAtNight":"N","hasBell":"Y","male":1,"female":3,"type":"공중화장실"},{"id":"202532400000100425","nm":"천호3동주민센터 화장실","lat":37.54,"lng":127.1298,"addr":"서울특별시 강동구 진황도로23길 7","isOpenAtNight":"N","hasBell":"N","male":2,"female":4,"type":"개방화장실"},{"id":"202532400000100304","nm":"게네 고덕천 물놀이장","lat":37.5526,"lng":127.173,"addr":"서울특별시 강동구 상일동 491","isOpenAtNight":"N","hasBell":"Y","male":1,"female":1,"type":"공중화장실"},{"id":"202532400000100368","nm":"의정부 부대찌개","lat":37.5522,"lng":127.128,"addr":"서울특별시 강동구 올림픽로 795","isOpenAtNight":"N","hasBell":"Y","male":2,"female":2,"type":"개방화장실"},{"id":"202532400000100372","nm":"웰빙메디컬빌딩","lat":37.5342,"lng":127.1366,"addr":"서울특별시 강동구 천호대로 1128","isOpenAtNight":"N","hasBell":"Y","male":2,"female":2,"type":"개방화장실"},{"id":"202532400000100407","nm":"복지둔촌충전소 화장실","lat":37.5251,"lng":127.1467,"addr":"서울특별시 강동구 둔촌동 115-1","isOpenAtNight":"N","hasBell":"N","male":2,"female":1,"type":"공중화장실"},{"id":"202532400000100462","nm":"5호선 강일역","lat":37.55758,"lng":127.17588,"addr":"서울특별시 강동구 고덕로 지하 456 강일역","isOpenAtNight":"N","hasBell":"Y","male":2,"female":8,"type":"개방화장실"},{"id":"202532400000100320","nm":"새장터어린이공원","lat":37.5522,"lng":127.1306,"addr":"서울특별시 강동구 암사1가길 16","isOpenAtNight":"N","hasBell":"Y","male":2,"female":3,"type":"공중화장실"},{"id":"202532400000100398","nm":"재건에너지재정제2주유소고속셀프지점","lat":37.5366,"lng":127.1494,"addr":"서울특별시 강동구 천호대로 1246","isOpenAtNight":"N","hasBell":"N","male":1,"female":2,"type":"공중화장실"},{"id":"202532400000100413","nm":"상일2동주민센터 화장실","lat":37.55,"lng":127.1758,"addr":"서울특별시 강동구 상일로6길 51","isOpenAtNight":"N","hasBell":"Y","male":2,"female":4,"type":"개방화장실"},{"id":"202532400000100373","nm":"남해빌딩","lat":37.5412,"lng":127.1409,"addr":"서울특별시 강동구 양재대로 1517","isOpenAtNight":"N","hasBell":"Y","male":2,"female":2,"type":"개방화장실"},{"id":"202532400000100321","nm":"광나루공원","lat":37.55,"lng":127.1255,"addr":"서울특별시 강동구 상암로 12-19","isOpenAtNight":"N","hasBell":"Y","male":1,"female":3,"type":"공중화장실"},{"id":"202532400000100343","nm":"일자산2체육관 화장실","lat":37.5281764,"lng":127.1509556,"addr":"서울특별시 강동구 동남로 620","isOpenAtNight":"N","hasBell":"Y","male":1,"female":1,"type":"개방화장실"},{"id":"202532400000100305","nm":"게내 수변공원(SK주유소 뒤)","lat":37.5605,"lng":127.1721,"addr":"서울특별시 강동구 강일동 703(공)","isOpenAtNight":"N","hasBell":"Y","male":1,"female":1,"type":"공중화장실"},{"id":"202532400000100309","nm":"고덕유수지 야구장 화장실","lat":37.5668,"lng":127.1649,"addr":"서울특별시 강동구 아리수로87길","isOpenAtNight":"N","hasBell":"Y","male":1,"female":2,"type":"공중화장실"},{"id":"202532400000100415","nm":"명일2동주민센터 화장실","lat":37.5463593,"lng":127.1513362,"addr":"서울특별시 강동구 상암로 260","isOpenAtNight":"N","hasBell":"Y","male":2,"female":2,"type":"개방화장실"},{"id":"202532400000100456","nm":"현대백화점 천호지점","lat":37.5391,"lng":127.1244,"addr":"서울특별시 강동구 천호대로 1005","isOpenAtNight":"N","hasBell":"Y","male":25,"female":128,"type":"개방화장실"},{"id":"202532400000100463","nm":"5호선 길동역","lat":37.537769,"lng":127.137803,"addr":"서울특별시 강동구 길동 378 길동역","isOpenAtNight":"N","hasBell":"Y","male":3,"female":7,"type":"개방화장실"},{"id":"202532400000100333","nm":"강동유소년스포츠센터 화장실","lat":37.5552978,"lng":127.1741901,"addr":"서울특별시 강동구 상일로12길 60","isOpenAtNight":"N","hasBell":"Y","male":2,"female":4,"type":"개방화장실"},{"id":"202532400000100461","nm":"5호선 고덕역","lat":37.555051,"lng":127.151921,"addr":"서울특별시 강동구 고덕동 310 고덕역","isOpenAtNight":"N","hasBell":"Y","male":3,"female":6,"type":"개방화장실"},{"id":"202532400000100409","nm":"강동구보건소 화장실","lat":37.5293,"lng":127.12555,"addr":"서울특별시 강동구 성내로 45","isOpenAtNight":"N","hasBell":"Y","male":2,"female":3,"type":"개방화장실"},{"id":"202532400000100345","nm":"천호1동공영주차장 화장실","lat":37.54489,"lng":127.1367,"addr":"서울특별시 강동구 구천면로 42길 60","isOpenAtNight":"N","hasBell":"Y","male":2,"female":2,"type":"개방화장실"},{"id":"202532400000100431","nm":"둔촌2동주민센터 화장실","lat":37.533283,"lng":127.141959,"addr":"서울특별시 강동구 천호대로186길 7","isOpenAtNight":"N","hasBell":"Y","male":0,"female":2,"type":"개방화장실"},{"id":"202532400000100346","nm":"천호3동 공영주차장 화장실","lat":37.53909,"lng":127.1332,"addr":"서울특별시 강동구 진황도로29길 34","isOpenAtNight":"N","hasBell":"Y","male":1,"female":0,"type":"개방화장실"},{"id":"202532400000100460","nm":"9호선 중앙보훈병원역","lat":37.5285,"lng":127.1484,"addr":"서울특별시 강동구 둔촌동 6-3","isOpenAtNight":"N","hasBell":"Y","male":3,"female":7,"type":"개방화장실"},{"id":"202532400000100379","nm":"신성통상","lat":37.5316,"lng":127.1404,"addr":"서울특별시 강동구 풍성로63길 84","isOpenAtNight":"N","hasBell":"Y","male":6,"female":3,"type":"개방화장실"},{"id":"202532400000100405","nm":"해뜨는 주유소","lat":37.5585,"lng":127.1714,"addr":"서울특별시 강동구 상일로 132","isOpenAtNight":"N","hasBell":"N","male":1,"female":2,"type":"공중화장실"},{"id":"202532400000100424","nm":"천호2동자치회관 화장실","lat":37.5426263,"lng":127.1206616,"addr":"서울특별시 강동구 구천면로 141","isOpenAtNight":"N","hasBell":"N","male":4,"female":4,"type":"개방화장실"},{"id":"202532400000100445","nm":"강동구청 고덕별관 화장실","lat":37.5569,"lng":127.1569,"addr":"서울특별시 강동구 동남로 930","isOpenAtNight":"N","hasBell":"Y","male":5,"female":4,"type":"개방화장실"},{"id":"202532400000100402","nm":"구천면 주유소","lat":37.5504,"lng":127.1383,"addr":"서울특별시 강동구 구천면로 357","isOpenAtNight":"N","hasBell":"N","male":1,"female":1,"type":"공중화장실"},{"id":"202532400000100423","nm":"천호2동주민센터 화장실","lat":37.5429,"lng":127.1271,"addr":"서울특별시 강동구 올림픽로80길 60","isOpenAtNight":"N","hasBell":"N","male":2,"female":4,"type":"개방화장실"},{"id":"202532400000100317","nm":"상일쉼터(그루터기)","lat":37.5528,"lng":127.1567,"addr":"서울특별시 강동구 상일동 147","isOpenAtNight":"N","hasBell":"Y","male":3,"female":5,"type":"공중화장실"},{"id":"202532400000100377","nm":"길동복조리시장 아름상가 고객화장실","lat":37.537,"lng":127.1432,"addr":"서울특별시 강동구 천호대로187길 62","isOpenAtNight":"N","hasBell":"N","male":1,"female":3,"type":"개방화장실"},{"id":"202532400000100420","nm":"암사2동주민센터 화장실","lat":37.551831,"lng":127.127265,"addr":"서울특별시 강동구 상암로3길 28","isOpenAtNight":"N","hasBell":"Y","male":1,"female":2,"type":"개방화장실"},{"id":"202532400000100331","nm":"산등성이목조식","lat":37.5616,"lng":127.1451,"addr":"서울특별시 강동구 암사동 산40-3","isOpenAtNight":"N","hasBell":"Y","male":1,"female":2,"type":"공중화장실"},{"id":"202532400000100342","nm":"일자산1체육관 화장실","lat":37.5330568,"lng":127.151191,"addr":"서울특별시 강동구 동남로 660","isOpenAtNight":"N","hasBell":"Y","male":2,"female":7,"type":"개방화장실"},{"id":"202532400000100436","nm":"별관 1층 화장실","lat":37.5284706,"lng":127.1479753,"addr":"서울특별시 강동구 진황도로 61길 53","isOpenAtNight":"N","hasBell":"N","male":2,"female":2,"type":"개방화장실"},{"id":"202532400000100327","nm":"볕우물어린이공원","lat":37.5536,"lng":127.1358,"addr":"서울특별시 강동구 고덕로24길 23","isOpenAtNight":"N","hasBell":"Y","male":1,"female":2,"type":"공중화장실"},{"id":"202532400000100426","nm":"성내1동주민센터 화장실","lat":37.5305,"lng":127.1225,"addr":"서울특별시 강동구 성내로 13","isOpenAtNight":"N","hasBell":"Y","male":8,"female":8,"type":"개방화장실"},{"id":"202532400000100361","nm":"홍익빌딩","lat":37.5343,"lng":127.1362,"addr":"서울특별시 강동구 천호대로 1124","isOpenAtNight":"N","hasBell":"Y","male":4,"female":4,"type":"개방화장실"},{"id":"202532400000100465","nm":"5호선 명일역","lat":37.55131,"lng":127.141825,"addr":"서울특별시 강동구 명일동 312 명일역","isOpenAtNight":"N","hasBell":"Y","male":3,"female":8,"type":"개방화장실"},{"id":"202532400000100401","nm":"(주)지유에너지직영 오렌지주유소","lat":37.5323,"lng":127.1332,"addr":"서울특별시 강동구 성안로 102","isOpenAtNight":"N","hasBell":"N","male":1,"female":1,"type":"공중화장실"},{"id":"202532400000100319","nm":"고분다리시장(주차장)","lat":37.5431,"lng":127.1322,"addr":"서울특별시 강동구 구천면로 258-6","isOpenAtNight":"N","hasBell":"Y","male":1,"female":2,"type":"공중화장실"},{"id":"202532400000100348","nm":"암사1동공영주차장 화장실","lat":37.55312,"lng":127.1379,"addr":"서울특별시 강동구 고덕로28길 36","isOpenAtNight":"N","hasBell":"Y","male":2,"female":2,"type":"개방화장실"},{"id":"202532400000100459","nm":"하나로마트 성내점","lat":37.5289,"lng":127.1204,"addr":"서울특별시 강동구 올림픽로 528","isOpenAtNight":"N","hasBell":"N","male":3,"female":3,"type":"개방화장실"},{"id":"202532400000100354","nm":"복원움집 뒤 화장실","lat":37.5611,"lng":127.1296,"addr":"서울특별시 강동구 올림픽로 875","isOpenAtNight":"N","hasBell":"Y","male":0,"female":2,"type":"개방화장실"},{"id":"202532400000100406","nm":"복지상일충전소 화장실","lat":37.5451,"lng":127.1698,"addr":"서울특별시 강동구 천호대로 1452","isOpenAtNight":"N","hasBell":"N","male":4,"female":1,"type":"공중화장실"},{"id":"202532400000100349","nm":"명일동공영주차장 화장실","lat":37.5512,"lng":127.1429,"addr":"서울특별시 강동구 구천면로 395","isOpenAtNight":"N","hasBell":"Y","male":2,"female":2,"type":"개방화장실"},{"id":"202532400000100453","nm":"강일도서관 화장실","lat":37.565132,"lng":127.173753,"addr":"서울특별시 강동구 아리수로 93길 9-14","isOpenAtNight":"N","hasBell":"Y","male":2,"female":3,"type":"개방화장실"},{"id":"202532400000100308","nm":"고덕초등학교 건너편","lat":37.5612,"lng":127.1682,"addr":"서울특별시 강동구 고덕로83길55","isOpenAtNight":"N","hasBell":"Y","male":0,"female":1,"type":"공중화장실"},{"id":"202532400000100457","nm":"이천일아울렛","lat":37.5412,"lng":127.1259,"addr":"서울특별시 강동구 구천면로 189","isOpenAtNight":"N","hasBell":"N","male":2,"female":3,"type":"개방화장실"},{"id":"202532400000100351","nm":"강일동공영주차장 화장실","lat":37.56627,"lng":127.1725,"addr":"서울특별시 강동구 아리수로91길 54","isOpenAtNight":"N","hasBell":"Y","male":1,"female":1,"type":"개방화장실"},{"id":"202532400000100300","nm":"일자산자연공원(도시농업공원)","lat":37.5339,"lng":127.1516,"addr":"서울특별시 강동구 둔촌2동 산119","isOpenAtNight":"N","hasBell":"Y","male":1,"female":1,"type":"공중화장실"},{"id":"202532400000100298","nm":"일자산자연공원(잔디광장옆)","lat":37.5314,"lng":127.1508,"addr":"서울특별시 강동구 둔촌동 산125","isOpenAtNight":"N","hasBell":"Y","male":1,"female":2,"type":"공중화장실"},{"id":"202532400000100353","nm":"수표소 뒤 화장실","lat":37.5595,"lng":127.1303,"addr":"서울특별시 강동구 올림픽로 875","isOpenAtNight":"N","hasBell":"N","male":2,"female":4,"type":"개방화장실"},{"id":"202532400000100350","nm":"천호유수지공영주차장 화장실","lat":37.54498,"lng":127.1219,"addr":"서울특별시 강동구 선사로 70","isOpenAtNight":"N","hasBell":"Y","male":0,"female":0,"type":"개방화장실"},{"id":"202532400000100325","nm":"암사역사공원 비지터센터","lat":37.5591,"lng":127.1311,"addr":"서울특별시 강동구 암사동 137-2(전)","isOpenAtNight":"N","hasBell":"Y","male":1,"female":2,"type":"공중화장실"},{"id":"202532400000100451","nm":"천호도서관 화장실","lat":37.540469,"lng":127.134048,"addr":"서울특별시 강동구 성안로 31마길 1","isOpenAtNight":"N","hasBell":"Y","male":2,"female":5,"type":"개방화장실"},{"id":"202532400000100395","nm":"대성석유㈜ 길동주유소","lat":37.5335,"lng":127.1411,"addr":"서울특별시 강동구 천호대로 1168","isOpenAtNight":"N","hasBell":"N","male":1,"female":2,"type":"공중화장실"},{"id":"202532400000100437","nm":"장례식장 2층 로비 화장실","lat":37.5280749,"lng":127.147635,"addr":"서울특별시 강동구 진황도로 61길 53","isOpenAtNight":"N","hasBell":"N","male":2,"female":4,"type":"개방화장실"},{"id":"202532400000100362","nm":"선린빌딩","lat":37.5351,"lng":127.1393,"addr":"서울특별시 강동구 양재대로 1448","isOpenAtNight":"N","hasBell":"Y","male":4,"female":4,"type":"개방화장실"},{"id":"202532400000100352","nm":"부설주차장 화장실","lat":37.5595,"lng":127.1303,"addr":"서울특별시 강동구 올림픽로 875","isOpenAtNight":"N","hasBell":"Y","male":2,"female":4,"type":"개방화장실"},{"id":"202532400000100364","nm":"중부빌딩","lat":37.5346,"lng":127.1378,"addr":"서울특별시 강동구 천호대로 1135","isOpenAtNight":"N","hasBell":"Y","male":4,"female":6,"type":"개방화장실"},{"id":"202532400000100455","nm":"신세계 이마트 천호지점 화장실","lat":37.5386,"lng":127.1256,"addr":"서울특별시 강동구 천호대로 1017","isOpenAtNight":"N","hasBell":"Y","male":2,"female":4,"type":"개방화장실"},{"id":"202532400000100444","nm":"강동구청 성안별관 화장실","lat":37.5306,"lng":127.1239,"addr":"서울특별시 강동구 성내로3가길 19","isOpenAtNight":"N","hasBell":"Y","male":1,"female":1,"type":"개방화장실"},{"id":"202532400000100337","nm":"샘터배드민턴장 화장실","lat":37.5618385,"lng":127.1590211,"addr":"서울특별시 강동구 동남로 990","isOpenAtNight":"N","hasBell":"Y","male":2,"female":4,"type":"개방화장실"},{"id":"202532400000100310","nm":"동명근린공원(배드민턴장)","lat":37.5597,"lng":127.1662,"addr":"서울특별시 강동구 고덕로83길55","isOpenAtNight":"N","hasBell":"Y","male":1,"female":2,"type":"공중화장실"},{"id":"202532400000100347","nm":"천호3동제2 공영주차장 화장실","lat":37.541,"lng":127.134,"addr":"서울특별시 강동구 성안로31마길 1","isOpenAtNight":"N","hasBell":"Y","male":0,"female":0,"type":"개방화장실"},{"id":"202532400000100324","nm":"암사역사공원","lat":37.5575,"lng":127.1305,"addr":"서울특별시 강동구 암사동 193(전)","isOpenAtNight":"N","hasBell":"Y","male":2,"female":6,"type":"공중화장실"},{"id":"202532400000100388","nm":"강동경찰서 화장실","lat":37.5286,"lng":127.1268,"addr":"서울특별시 강동구 성내로 57 (성내동)","isOpenAtNight":"N","hasBell":"Y","male":2,"female":2,"type":"개방화장실"},{"id":"202532400000100335","nm":"강일테니스장 화장실","lat":37.5703848,"lng":127.1718413,"addr":"서울특별시 강동구 아리수로93가길 314","isOpenAtNight":"N","hasBell":"N","male":1,"female":2,"type":"개방화장실"},{"id":"202532400000100306","nm":"게내 수변공원(공원관리소)","lat":37.5557,"lng":127.1726,"addr":"서울특별시 강동구 상일동 479","isOpenAtNight":"N","hasBell":"Y","male":1,"female":3,"type":"공중화장실"},{"id":"202532400000100313","nm":"샘터근린공원(족구장)","lat":37.5627,"lng":127.1576,"addr":"서울특별시 강동구 동남로 990","isOpenAtNight":"N","hasBell":"Y","male":1,"female":4,"type":"공중화장실"}]}