{"items":[{"id":"202431600000100531","nm":"오류시장","lat":37.49668227081,"lng":126.8437846221,"addr":"서울특별시 구로구 경인로19가길 14-1","isOpenAtNight":"N","hasBell":"N","male":2,"female":4,"type":"개방화장실"},{"id":"202431600000100552","nm":"시티월드상가","lat":37.49441156902,"lng":126.8410150665,"addr":"서울특별시 구로구 경인로 176","isOpenAtNight":"N","hasBell":"N","male":3,"female":3,"type":"개방화장실"},{"id":"202431600000100607","nm":"현대백화점 디큐브시티 6층","lat":37.50812171935,"lng":126.8885003799,"addr":"서울특별시 구로구 경인로 662 (신도림동, 디큐브시티)","isOpenAtNight":"N","hasBell":"Y","male":2,"female":4,"type":"개방화장실"},{"id":"202431600000100564","nm":"신성주유소","lat":37.4953143684,"lng":126.8823910254,"addr":"서울특별시 구로구 구로동로 187(구로동)","isOpenAtNight":"N","hasBell":"N","male":1,"female":1,"type":"개방화장실"},{"id":"202431600000100550","nm":"서울축산정육식당","lat":37.5010049048,"lng":126.8896123137,"addr":"서울특별시 구로구 공원로 47","isOpenAtNight":"N","hasBell":"N","male":3,"female":5,"type":"개방화장실"},{"id":"202431600000100594","nm":"NC 신구로점 6층-2","lat":37.50115349156,"lng":126.8824285072,"addr":"서울특별시 구로구 구로중앙로152","isOpenAtNight":"N","hasBell":"N","male":0,"female":3,"type":"개방화장실"},{"id":"202431600000100599","nm":"현대백화점 디큐브시티1층","lat":37.50812171935,"lng":126.8885003799,"addr":"서울특별시 구로구 경인로 662 (신도림동, 디큐브시티)","isOpenAtNight":"N","hasBell":"Y","male":4,"female":8,"type":"개방화장실"},{"id":"202431600000100591","nm":"NC 신구로점 5층-1","lat":37.50115349156,"lng":126.8824285072,"addr":"서울특별시 구로구 구로중앙로152","isOpenAtNight":"N","hasBell":"N","male":3,"female":3,"type":"개방화장실"},{"id":"202431600000100579","nm":"오승프라임산업(주) 궁동LPG충전소","lat":37.50706330604,"lng":126.8292378063,"addr":"서울특별시 구로구 궁동1-16,2","isOpenAtNight":"N","hasBell":"N","male":2,"female":2,"type":"개방화장실"},{"id":"202431600000100605","nm":"현대백화점 디큐브시티 5층-2","lat":37.50812171935,"lng":126.8885003799,"addr":"서울특별시 구로구 경인로 662 (신도림동, 디큐브시티)","isOpenAtNight":"N","hasBell":"Y","male":3,"female":5,"type":"개방화장실"},{"id":"202431600000100586","nm":"NC 신구로점 2층-2","lat":37.50115349156,"lng":126.8824285072,"addr":"서울특별시 구로구 구로중앙로152","isOpenAtNight":"N","hasBell":"N","male":0,"female":3,"type":"개방화장실"},{"id":"202431600000100578","nm":"대성산업㈜ 오류동충전소","lat":37.49279268809,"lng":126.8376475608,"addr":"서울특별시 구로구 오류동74-8","isOpenAtNight":"N","hasBell":"N","male":2,"female":1,"type":"개방화장실"},{"id":"202431600000100529","nm":"황토생고기집","lat":37.49425157674,"lng":126.8881742187,"addr":"서울특별시 구로구 구로중앙로19길 19","isOpenAtNight":"N","hasBell":"N","male":1,"female":1,"type":"개방화장실"},{"id":"202431600000100581","nm":"고척스카이돔 관리동","lat":37.49821433971,"lng":126.8670917943,"addr":"서울특별시 구로구 경인로 430(고척스카이돔)","isOpenAtNight":"N","hasBell":"Y","male":1,"female":3,"type":"공중화장실"},{"id":"202431600000100544","nm":"삼성디지털프라자 개봉점","lat":37.49638024333,"lng":126.8609448223,"addr":"서울특별시 구로구 경인로 368","isOpenAtNight":"N","hasBell":"N","male":1,"female":1,"type":"개방화장실"},{"id":"202431600000100576","nm":"동일석유㈜ 남부충전소","lat":37.48429866899,"lng":126.9020709692,"addr":"서울특별시 구로구 구로3동1123-2","isOpenAtNight":"N","hasBell":"N","male":1,"female":2,"type":"공중화장실"},{"id":"202431600000100608","nm":"테크노마트 지하2층","lat":37.50704764491,"lng":126.8902241736,"addr":"서울특별시 구로구 새말로 97 (구로동, 신도림테크노마트)","isOpenAtNight":"N","hasBell":"Y","male":6,"female":13,"type":"개방화장실"},{"id":"202431600000100598","nm":"현대백화점 디큐브시티 지하1층-1","lat":37.50812171935,"lng":126.8885003799,"addr":"서울특별시 구로구 경인로 662 (신도림동, 디큐브시티)","isOpenAtNight":"N","hasBell":"Y","male":4,"female":5,"type":"개방화장실"},{"id":"202431600000100597","nm":"현대백화점 디큐브시티 지하1층-2","lat":37.50812171935,"lng":126.8885003799,"addr":"서울특별시 구로구 경인로 662 (신도림동, 디큐브시티)","isOpenAtNight":"N","hasBell":"Y","male":3,"female":5,"type":"개방화장실"},{"id":"202431600000100589","nm":"NC 신구로점 4층-1","lat":37.50115349156,"lng":126.8824285072,"addr":"서울특별시 구로구 구로중앙로152","isOpenAtNight":"N","hasBell":"N","male":3,"female":5,"type":"개방화장실"},{"id":"202431600000100563","nm":"구인주유소","lat":37.50243478711,"lng":126.8797629368,"addr":"서울특별시 구로구 경인로 558(구로동)","isOpenAtNight":"N","hasBell":"N","male":1,"female":1,"type":"개방화장실"},{"id":"202431600000100604","nm":"현대백화점 디큐브시티 4층","lat":37.50812171935,"lng":126.8885003799,"addr":"서울특별시 구로구 경인로 662 (신도림동, 디큐브시티)","isOpenAtNight":"N","hasBell":"Y","male":3,"female":6,"type":"개방화장실"},{"id":"202431600000100557","nm":"SK구로주유소","lat":37.49370369456,"lng":126.8721808171,"addr":"서울특별시 구로구 구일로 94(구로동)","isOpenAtNight":"N","hasBell":"N","male":1,"female":1,"type":"개방화장실"},{"id":"202431600000100554","nm":"고척근린시장","lat":37.50199442635,"lng":126.8498439748,"addr":"서울특별시 구로구 고척로32길 11-4","isOpenAtNight":"N","hasBell":"N","male":2,"female":2,"type":"개방화장실"},{"id":"202431600000100533","nm":"고척산업용품종합상가-2","lat":37.49982343379,"lng":126.860134852,"addr":"서울특별시 구로구 중앙로3길 50","isOpenAtNight":"N","hasBell":"N","male":2,"female":2,"type":"개방화장실"},{"id":"202431600000100609","nm":"고척프라자2층","lat":37.50348750044,"lng":126.8626126412,"addr":"서울특별시 구로구 중앙로10길 7 (고척동)","isOpenAtNight":"N","hasBell":"N","male":2,"female":3,"type":"공중화장실"},{"id":"202431600000100571","nm":"처음처럼주유소","lat":37.49739250135,"lng":126.8289702012,"addr":"서울특별시 구로구 오리로 1299(궁동)","isOpenAtNight":"N","hasBell":"N","male":1,"female":2,"type":"공중화장실"},{"id":"202431600000100588","nm":"NC 신구로점 3층-2","lat":37.50115349156,"lng":126.8824285072,"addr":"서울특별시 구로구 구로중앙로152","isOpenAtNight":"N","hasBell":"N","male":0,"female":3,"type":"개방화장실"},{"id":"202431600000100548","nm":"광진빌딩","lat":37.49481492919,"lng":126.8886747673,"addr":"서울특별시 구로구 가마산로 250","isOpenAtNight":"N","hasBell":"N","male":2,"female":2,"type":"개방화장실"},{"id":"202431600000100573","nm":"SK에너지(주) 개봉동주유소","lat":37.49763952209,"lng":126.8523308317,"addr":"서울특별시 구로구 경인로 290(개봉동)","isOpenAtNight":"N","hasBell":"N","male":1,"female":1,"type":"개방화장실"},{"id":"202431600000100541","nm":"고척산업용품종합상가-4","lat":37.49982343379,"lng":126.860134852,"addr":"서울특별시 구로구 중앙로3길 50","isOpenAtNight":"N","hasBell":"N","male":2,"female":2,"type":"개방화장실"},{"id":"202431600000100555","nm":"은산빌딩","lat":37.50176221493,"lng":126.8772509095,"addr":"서울특별시 구로구 경인로 53길 8","isOpenAtNight":"N","hasBell":"N","male":2,"female":3,"type":"개방화장실"},{"id":"202431600000100565","nm":"영진주유소","lat":37.48370747732,"lng":126.8870186894,"addr":"서울특별시 구로구 구로동로 20(가리봉동)","isOpenAtNight":"N","hasBell":"N","male":1,"female":1,"type":"개방화장실"},{"id":"202431600000100543","nm":"개봉제일교회","lat":37.5019716783,"lng":126.849358006,"addr":"서울특별시 구로구 고척로30길 13-13","isOpenAtNight":"N","hasBell":"N","male":1,"female":2,"type":"개방화장실"},{"id":"202431600000100596","nm":"NC 신구로점 7층-2","lat":37.50115349156,"lng":126.8824285072,"addr":"서울특별시 구로구 구로중앙로152","isOpenAtNight":"N","hasBell":"N","male":0,"female":3,"type":"개방화장실"},{"id":"202431600000100537","nm":"현대백화점 디큐브시티 지하2층-2","lat":37.50812171935,"lng":126.8885003799,"addr":"서울특별시 구로구 경인로 662 (신도림동, 디큐브시티)","isOpenAtNight":"N","hasBell":"Y","male":2,"female":5,"type":"개방화장실"},{"id":"202431600000100551","nm":"한우가","lat":37.50235467081,"lng":126.8884613682,"addr":"서울특별시 구로구 공원로 67","isOpenAtNight":"N","hasBell":"N","male":2,"female":2,"type":"개방화장실"},{"id":"202431600000100558","nm":"구로주유소","lat":37.49101812088,"lng":126.8835292337,"addr":"서울특별시 구로구 구로동로 137(구로동)","isOpenAtNight":"N","hasBell":"N","male":1,"female":2,"type":"개방화장실"},{"id":"202431600000100602","nm":"현대백화점 디큐브시티 3층-2","lat":37.50812171935,"lng":126.8885003799,"addr":"서울특별시 구로구 경인로 662 (신도림동, 디큐브시티)","isOpenAtNight":"N","hasBell":"Y","male":3,"female":4,"type":"개방화장실"},{"id":"202431600000100549","nm":"이마트 구로점","lat":37.48439490825,"lng":126.8978859332,"addr":"서울특별시 구로구 디지털로32길 43","isOpenAtNight":"N","hasBell":"N","male":2,"female":5,"type":"개방화장실"},{"id":"202431600000100566","nm":"근린공원주유소","lat":37.50510368718,"lng":126.8554853522,"addr":"서울특별시 구로구 고척로 199(고척동)","isOpenAtNight":"N","hasBell":"N","male":1,"female":2,"type":"개방화장실"},{"id":"202431600000100559","nm":"현대오일뱅크(주)직영 구로셀프주유소","lat":37.48094746103,"lng":126.8992367665,"addr":"서울특별시 구로구 시흥대로 531(구로동)","isOpenAtNight":"N","hasBell":"N","male":1,"female":2,"type":"개방화장실"},{"id":"202431600000100560","nm":"㈜한미석유 구로그린주유소","lat":37.49642449472,"lng":126.888322986,"addr":"서울특별시 구로구 구로중앙로 76(구로동)","isOpenAtNight":"N","hasBell":"N","male":2,"female":2,"type":"개방화장실"},{"id":"202431600000100540","nm":"고척산업용품종합상가-3","lat":37.49982343379,"lng":126.860134852,"addr":"서울특별시 구로구 중앙로3길 50","isOpenAtNight":"N","hasBell":"N","male":2,"female":2,"type":"개방화장실"},{"id":"202431600000100587","nm":"NC 신구로점 3층-1","lat":37.50115349156,"lng":126.8824285072,"addr":"서울특별시 구로구 구로중앙로152","isOpenAtNight":"N","hasBell":"N","male":1,"female":5,"type":"개방화장실"},{"id":"202431600000100580","nm":"고척스카이돔 동측","lat":37.49821433971,"lng":126.8670917943,"addr":"서울특별시 구로구 경인로 430(고척스카이돔)","isOpenAtNight":"N","hasBell":"Y","male":2,"female":8,"type":"공중화장실"},{"id":"202431600000100570","nm":"현대오일뱅크(주)직영 신오류주유소","lat":37.49438725915,"lng":126.8394548615,"addr":"서울특별시 구로구 경인로 161(오류동)","isOpenAtNight":"N","hasBell":"N","male":1,"female":1,"type":"공중화장실"},{"id":"202431600000100572","nm":"서울석유(주) 풀페이주유소","lat":37.49098169027,"lng":126.826706804,"addr":"서울특별시 구로구 경인로 41(온수동)","isOpenAtNight":"N","hasBell":"N","male":2,"female":2,"type":"개방화장실"},{"id":"202431600000100575","nm":"한일가스산업(주)","lat":37.5019212733,"lng":126.8778705656,"addr":"서울특별시 구로구 구로동600-6","isOpenAtNight":"N","hasBell":"N","male":2,"female":1,"type":"개방화장실"},{"id":"202431600000100562","nm":"동아주유소","lat":37.49083848615,"lng":126.8931776849,"addr":"서울특별시 구로구 도림로 91(구로동)","isOpenAtNight":"N","hasBell":"N","male":1,"female":2,"type":"개방화장실"},{"id":"202431600000100542","nm":"가리봉시장","lat":37.48164069757,"lng":126.8885757117,"addr":"서울특별시 구로구 우마3길 5","isOpenAtNight":"N","hasBell":"N","male":1,"female":1,"type":"개방화장실"},{"id":"202431600000100583","nm":"NC 신구로점 지하1층-2","lat":37.50115349156,"lng":126.8824285072,"addr":"서울특별시 구로구 구로중앙로152","isOpenAtNight":"N","hasBell":"N","male":2,"female":5,"type":"개방화장실"},{"id":"202431600000100545","nm":"송림가","lat":37.49699867442,"lng":126.8643507488,"addr":"서울특별시 구로구 경인로 398","isOpenAtNight":"N","hasBell":"N","male":1,"female":2,"type":"개방화장실"},{"id":"202431600000100601","nm":"현대백화점 디큐브시티 2층-1","lat":37.50812171935,"lng":126.8885003799,"addr":"서울특별시 구로구 경인로 662 (신도림동, 디큐브시티)","isOpenAtNight":"N","hasBell":"Y","male":1,"female":5,"type":"개방화장실"},{"id":"202431600000100569","nm":"동선주유소","lat":37.49327916479,"lng":126.8385560092,"addr":"서울특별시 구로구 경인로 150(오류동)","isOpenAtNight":"N","hasBell":"N","male":1,"female":1,"type":"개방화장실"},{"id":"202431600000100553","nm":"대성빌딩","lat":37.49240744221,"lng":126.843386809,"addr":"서울특별시 구로구 오류로8길 57","isOpenAtNight":"N","hasBell":"N","male":2,"female":2,"type":"개방화장실"},{"id":"202431600000100535","nm":"구로성심병원(별관)","lat":37.49964897423,"lng":126.8663576544,"addr":"서울특별시 구로구 중앙로 10-15 (고척동, 구로성심병원별관)","isOpenAtNight":"N","hasBell":"N","male":2,"female":3,"type":"공중화장실"},{"id":"202431600000100600","nm":"현대백화점 디큐브시티 2층-2","lat":37.50812171935,"lng":126.8885003799,"addr":"서울특별시 구로구 경인로 662 (신도림동, 디큐브시티)","isOpenAtNight":"N","hasBell":"Y","male":2,"female":3,"type":"개방화장실"},{"id":"202431600000100585","nm":"NC 신구로점 2층-1","lat":37.50115349156,"lng":126.8824285072,"addr":"서울특별시 구로구 구로중앙로152","isOpenAtNight":"N","hasBell":"N","male":3,"female":3,"type":"개방화장실"},{"id":"202431600000100561","nm":"현대오일뱅크(주)직영 신구로주유소","lat":37.4975529052,"lng":126.8923888568,"addr":"서울특별시 구로구 가마산로 293(구로동)","isOpenAtNight":"N","hasBell":"N","male":2,"female":2,"type":"개방화장실"},{"id":"202431600000100574","nm":"극동유화(주) 항동주유소","lat":37.48346001263,"lng":126.8278193115,"addr":"서울특별시 구로구 서해안로 2154(항동)","isOpenAtNight":"N","hasBell":"N","male":1,"female":1,"type":"개방화장실"},{"id":"202431600000100610","nm":"고척프라자1층","lat":37.50348750044,"lng":126.8626126412,"addr":"서울특별시 구로구 중앙로10길 7 (고척동)","isOpenAtNight":"N","hasBell":"N","male":2,"female":3,"type":"공중화장실"},{"id":"202431600000100584","nm":"NC 신구로점 1층","lat":37.50115349156,"lng":126.8824285072,"addr":"서울특별시 구로구 구로중앙로152","isOpenAtNight":"N","hasBell":"Y","male":3,"female":3,"type":"개방화장실"},{"id":"202431600000100603","nm":"현대백화점 디큐브시티 3층-1","lat":37.50812171935,"lng":126.8885003799,"addr":"서울특별시 구로구 경인로 662 (신도림동, 디큐브시티)","isOpenAtNight":"N","hasBell":"Y","male":3,"female":4,"type":"개방화장실"},{"id":"202431600000100592","nm":"NC 신구로점 5층-2","lat":37.50115349156,"lng":126.8824285072,"addr":"서울특별시 구로구 구로중앙로152","isOpenAtNight":"N","hasBell":"N","male":0,"female":3,"type":"개방화장실"},{"id":"202431600000100536","nm":"홈플러스(신도림점) 지하1층","lat":37.5100393992,"lng":126.8883362466,"addr":"서울특별시 구로구 경인로 661 (신도림동, 신도림1차푸르지오)","isOpenAtNight":"N","hasBell":"Y","male":5,"female":10,"type":"공중화장실"},{"id":"202431600000100556","nm":"대성산업(주) 디큐브주유소","lat":37.50770067015,"lng":126.8868439558,"addr":"서울특별시 구로구 경인로 650(신도림동)","isOpenAtNight":"N","hasBell":"N","male":1,"female":1,"type":"개방화장실"},{"id":"202431600000100590","nm":"NC 신구로점 4층-2","lat":37.50115349156,"lng":126.8824285072,"addr":"서울특별시 구로구 구로중앙로152","isOpenAtNight":"N","hasBell":"N","male":2,"female":0,"type":"개방화장실"},{"id":"202431600000100595","nm":"NC 신구로점 7층-1","lat":37.50115349156,"lng":126.8824285072,"addr":"서울특별시 구로구 구로중앙로152","isOpenAtNight":"N","hasBell":"N","male":2,"female":2,"type":"개방화장실"},{"id":"202431600000100577","nm":"개봉충전소","lat":37.49658429444,"lng":126.8606137684,"addr":"서울특별시 구로구 개봉동175-16","isOpenAtNight":"N","hasBell":"N","male":1,"female":2,"type":"개방화장실"},{"id":"202431600000100546","nm":"실크로드","lat":37.49699867442,"lng":126.8643507488,"addr":"서울특별시 구로구 경인로 398","isOpenAtNight":"N","hasBell":"N","male":1,"female":2,"type":"개방화장실"},{"id":"202431600000100593","nm":"NC 신구로점 6층-1","lat":37.50115349156,"lng":126.8824285072,"addr":"서울특별시 구로구 구로중앙로152","isOpenAtNight":"N","hasBell":"N","male":3,"female":3,"type":"개방화장실"},{"id":"202431600000100582","nm":"NC 신구로점 지하1층-1","lat":37.50115349156,"lng":126.8824285072,"addr":"서울특별시 구로구 구로중앙로152","isOpenAtNight":"N","hasBell":"N","male":3,"female":3,"type":"개방화장실"},{"id":"202431600000100567","nm":"개봉주유소","lat":37.5018930623,"lng":126.8468371496,"addr":"서울특별시 구로구 고척로 115(개봉동)","isOpenAtNight":"N","hasBell":"N","male":1,"female":1,"type":"개방화장실"},{"id":"202431600000100532","nm":"고척산업용품종합상가-1","lat":37.49982343379,"lng":126.860134852,"addr":"서울특별시 구로구 중앙로3길 50","isOpenAtNight":"N","hasBell":"N","male":2,"female":2,"type":"개방화장실"},{"id":"202431600000100539","nm":"현대백화점 디큐브시티 지하2층-3","lat":37.50812171935,"lng":126.8885003799,"addr":"서울특별시 구로구 경인로 662 (신도림동, 디큐브시티)","isOpenAtNight":"N","hasBell":"Y","male":4,"female":6,"type":"개방화장실"},{"id":"202431600000100538","nm":"현대백화점 디큐브시티 지하2층-1","lat":37.50812171935,"lng":126.8885003799,"addr":"서울특별시 구로구 경인로 662 (신도림동, 디큐브시티)","isOpenAtNight":"N","hasBell":"N","male":3,"female":5,"type":"개방화장실"},{"id":"202431600000100530","nm":"솔로몬자동차","lat":37.50335653549,"lng":126.8453783078,"addr":"서울특별시 구로구 고척로21길 43","isOpenAtNight":"N","hasBell":"N","male":1,"female":1,"type":"개방화장실"},{"id":"202431600000100534","nm":"구로성심병원(본관)","lat":37.49964897423,"lng":126.8663576544,"addr":"서울특별시 구로구 경인로 427 (고척동, 구로성심병원)","isOpenAtNight":"N","hasBell":"Y","male":1,"female":3,"type":"공중화장실"},{"id":"202431600000100547","nm":"개성면옥","lat":37.4929039233,"lng":126.8838065226,"addr":"서울특별시 구로구 가마산로 204","isOpenAtNight":"N","hasBell":"N","male":1,"female":1,"type":"개방화장실"},{"id":"202431600000100606","nm":"현대백화점 디큐브시티 5층-1","lat":37.50812171935,"lng":126.8885003799,"addr":"서울특별시 구로구 경인로 662 (신도림동, 디큐브시티)","isOpenAtNight":"N","hasBell":"Y","male":3,"female":6,"type":"개방화장실"},{"id":"202431600000100568","nm":"㈜새서울석유 대원주유소","lat":37.48620631458,"lng":126.8561578251,"addr":"서울특별시 구로구 개봉로 7(개봉동)","isOpenAtNight":"N","hasBell":"N","male":1,"female":2,"type":"개방화장실"}]}